aggify/__init__.py
aggify/aggify.py
aggify/compiler.py
aggify/exceptions.py
aggify/types.py
aggify/utilty.py
aggify-0.3.9.dist-info/LICENSE
aggify-0.3.9.dist-info/METADATA
aggify-0.3.9.dist-info/WHEEL
aggify-0.3.9.dist-info/RECORD
