Metadata-Version: 2.1
Name: aggify
Version: 0.3.9
Summary: A MongoDB aggregation generator for Mongoengine
Home-page: https://github.com/Aggify/aggify
Author: SeYeD.Dev
Author-email: me@seyed.dev
Requires-Python: >=3.8,<4.0
Classifier: Programming Language :: Python :: 3
Classifier: Programming Language :: Python :: 3.8
Classifier: Programming Language :: Python :: 3.9
Classifier: Programming Language :: Python :: 3.10
Classifier: Programming Language :: Python :: 3.11
Classifier: Programming Language :: Python :: 3.12
Requires-Dist: mongoengine (>=0.27.0)
Project-URL: Documentation, https://github.com/Aggify/aggify/docs
Project-URL: Repository, https://github.com/Aggify/aggify
